lodestone/__init__.py
lodestone/__main__.py
lodestone/bot.py
lodestone/server.py
lodestone/data/facingData.json
lodestone/data/interactable.json
lodestone/experimental/__init__.py
lodestone/experimental/tasks/tasks.py
lodestone/modules/__init__.py
lodestone/modules/api.py
lodestone/modules/console.py
lodestone/modules/exceptions.py
lodestone/modules/logger.py
lodestone/modules/lstream.py
lodestone/utils/__init__.py
lodestone/utils/_types.py
lodestone/utils/utils.py
lodestone-0.1.11.dist-info/LICENSE.txt
lodestone-0.1.11.dist-info/WHEEL
lodestone-0.1.11.dist-info/METADATA
lodestone-0.1.11.dist-info/RECORD
