Metadata-Version: 2.1
Name: lodestone
Version: 0.1.11
Summary: 🤖 Create Minecraft bots with a powerful, stable, and high level Python API.
Author-email: Silke Pilon <silkepilon2009@gmail.com>, HellishBro <hellishbro@outlook.com>, Levy <Levy@example.com>
Requires-Python: >=3.10
Requires-Dist: javascript
Requires-Dist: click
Requires-Dist: rich
Requires-Dist: fastapi
Requires-Dist: structlog
Requires-Dist: uvicorn
Requires-Dist: tinydb
Requires-Dist: fuzzyfinder
Requires-Dist: requests
Requires-Dist: python-dotenv
Requires-Dist: aiofiles
Requires-Dist: gradio==3.*
Requires-Dist: psutil
Requires-Dist: prompt_toolkit
Project-URL: Documentation, https://github.com/SilkePilon/Lodestone/blob/main/README.md
Project-URL: Homepage, https://github.com/SilkePilon/Lodestone
Project-URL: Repository, https://github.com/SilkePilon/Lodestone
